odoo/addons/stock_reception_screen_mrp_subcontracting/README.rst
odoo/addons/stock_reception_screen_mrp_subcontracting/__init__.py
odoo/addons/stock_reception_screen_mrp_subcontracting/__manifest__.py
odoo/addons/stock_reception_screen_mrp_subcontracting/i18n/stock_reception_screen_mrp_subcontracting.pot
odoo/addons/stock_reception_screen_mrp_subcontracting/models/__init__.py
odoo/addons/stock_reception_screen_mrp_subcontracting/models/stock_move.py
odoo/addons/stock_reception_screen_mrp_subcontracting/models/stock_move_line.py
odoo/addons/stock_reception_screen_mrp_subcontracting/models/stock_reception_screen.py
odoo/addons/stock_reception_screen_mrp_subcontracting/readme/CONTRIBUTORS.rst
odoo/addons/stock_reception_screen_mrp_subcontracting/readme/DESCRIPTION.rst
odoo/addons/stock_reception_screen_mrp_subcontracting/static/description/icon.png
odoo/addons/stock_reception_screen_mrp_subcontracting/static/description/index.html
odoo/addons/stock_reception_screen_mrp_subcontracting/tests/__init__.py
odoo/addons/stock_reception_screen_mrp_subcontracting/tests/test_reception_screen.py
odoo/addons/stock_reception_screen_mrp_subcontracting/wizards/__init__.py
odoo/addons/stock_reception_screen_mrp_subcontracting/wizards/mrp_product_produce.py
odoo13_addon_stock_reception_screen_mrp_subcontracting-13.0.1.0.1.dist-info/METADATA
odoo13_addon_stock_reception_screen_mrp_subcontracting-13.0.1.0.1.dist-info/WHEEL
odoo13_addon_stock_reception_screen_mrp_subcontracting-13.0.1.0.1.dist-info/top_level.txt
odoo13_addon_stock_reception_screen_mrp_subcontracting-13.0.1.0.1.dist-info/RECORD
